{
  "name": "Bellhop",
  "version": "1.2.0",
  "main": "dist/bellhop.min.js",
  "dependencies": {
    "bind-polyfill": "*"
  },
  "devDependencies": {
    "jquery": "*",
    "qunit": "*",
    "google-code-prettify": "*",
    "bind-polyfill": "*"
  },
  "ignore": [
    "src",
    "example",
    "package.json",
    "tasks",
    "Gruntfile.js",
    ".travis.yml",
    "library.json",
    ".jsbeautifyrc",
    ".editorconfig",
    ".gitignore",
    ".gitattributes"
  ],
  "homepage": "https://github.com/SpringRoll/Bellhop",
  "_release": "1.2.0",
  "_resolution": {
    "type": "version",
    "tag": "1.2.0",
    "commit": "9d05a63ecde26d1bc2c2e4949f210774bc3bd9d4"
  },
  "_source": "git://github.com/SpringRoll/Bellhop.git",
  "_target": "*",
  "_originalSource": "bellhop"
}